cz_trailers/__init__.py
cz_trailers/cz_trailers.py
cz_trailers/templates/CHANGELOG.md.j2
cz_trailers-0.2.0.dist-info/METADATA
cz_trailers-0.2.0.dist-info/WHEEL
cz_trailers-0.2.0.dist-info/entry_points.txt
cz_trailers-0.2.0.dist-info/top_level.txt
cz_trailers-0.2.0.dist-info/RECORD
