Metadata-Version: 2.1
Name: cz-trailers
Version: 0.2.0
Requires-Dist: commitizen
